{"file":{"path":"C:\\Users\\t-skothapall\\AppData\\Local\\Temp\\jfjkrzxi.1ol\\C\\msys64\\ucrt64\\include\\sec_api\\stdio_s.h","sha256":"EFF3F774012CC2B506E0A7ABC79D3A997E504B3959A393E79B60446448A163CE","written":"2024-12-09T07:03:02.0648600Z"},
"operations":[
{"row":0,"command":"#pragma","args":["once"]},
{"row":6,"command":"#ifndef","args":["_INC_STDIO_S"]},
{"row":7,"command":"#define","args":["_INC_STDIO_S"," "]},
{"row":9,"command":"#include","args":["\u003Cstdio.h\u003E"]},
{"row":11,"command":"#if","args":["defined","(","__LIBMSVCRT__",")"]},
{"row":13,"command":"#define","args":["_SECIMP"," "]},
{"row":14,"command":"#else","args":[]},
{"row":15,"command":"#ifndef","args":["_SECIMP"]},
{"row":16,"command":"#define","args":["_SECIMP"," ","__declspec","(","dllimport",")"]},
{"row":17,"command":"#endif","args":[]},
{"row":18,"command":"#endif","args":[]},
{"row":20,"command":"#ifdef","args":["__cplusplus"]},
{"row":21,"command":"","args":["extern"]},
{"row":22,"command":"#endif","args":[]},
{"row":24,"command":"#ifndef","args":["_STDIO_S_DEFINED"]},
{"row":25,"command":"#define","args":["_STDIO_S_DEFINED"," "]},
{"row":26,"command":"#define","args":["L_tmpnam_s"," ","L_tmpnam"]},
{"row":27,"command":"#define","args":["TMP_MAX_S"," ","TMP_MAX"]},
{"row":29,"command":"","args":["__cdecl","_Count","_CRTIMP","_DstBuf","_DstSize","_ElementSize","_File","clearerr_s","errno_t","FILE","fread_s","size_t","void"]},
{"row":33,"command":"#ifdef","args":["_UCRT"]},
{"row":34,"command":"","args":["__builtin_va_end","__builtin_va_list","__builtin_va_start","__cdecl","__int64","__mingw_ovr","__stdio_common_vfprintf","__stdio_common_vfprintf_p","__stdio_common_vfprintf_s","__stdio_common_vfscanf","__stdio_common_vsnprintf_s","__stdio_common_vsprintf","__stdio_common_vsprintf_p","__stdio_common_vsprintf_s","__stdio_common_vsscanf","_ArgList","_CRT_INTERNAL_PRINTF_LEGACY_VSPRINTF_NULL_TERMINATION","_CRT_INTERNAL_PRINTF_STANDARD_SNPRINTF_BEHAVIOR","_CRT_INTERNAL_SCANF_SECURECRT","_Dst","_DstBuf","_DstSize","_File","_Format","_fprintf_l","_fprintf_p","_fprintf_p_l","_fprintf_s_l","_fscanf_l","_fscanf_s_l","_Len","_Locale","_locale_t","_MaxCount","_Options","_printf_l","_printf_p","_printf_p_l","_printf_s_l","_Ret","_scanf_l","_scanf_s_l","_scprintf_l","_scprintf_p","_scprintf_p_l","_Size","_snprintf_c","_snprintf_c_l","_snprintf_l","_snprintf_s","_snprintf_s_l","_snscanf_l","_snscanf_s","_snscanf_s_l","_sprintf_l","_sprintf_p","_sprintf_p_l","_sprintf_s_l","_Src","_sscanf_l","_sscanf_s_l","_Str","_vfprintf_l","_vfprintf_p","_vfprintf_p_l","_vfprintf_s_l","_vfscanf_l","_vfscanf_s_l","_vprintf_l","_vprintf_p","_vprintf_p_l","_vprintf_s_l","_vscanf_l","_vscanf_s_l","_vscprintf_l","_vscprintf_p","_vscprintf_p_l","_vsnprintf_c","_vsnprintf_c_l","_vsnprintf_l","_vsnprintf_s","_vsnprintf_s_l","_vsprintf_l","_vsprintf_p","_vsprintf_p_l","_vsprintf_s_l","_vsscanf_l","_vsscanf_s_l","char","const","FILE","fprintf_s","fscanf_s","int","NULL","printf_s","return","scanf_s","size_t","sprintf_s","sscanf_s","stdin","stdout","unsigned","va_list","vfprintf_s","vfscanf_s","vprintf_s","vscanf_s","vsnprintf_s","vsprintf_s","vsscanf_s"]},
{"row":514,"command":"#else","args":[]},
{"row":515,"command":"","args":["__cdecl","_ArgList","_CRTIMP","_Dst","_DstBuf","_DstSize","_File","_Format","_fprintf_l","_fprintf_p","_fprintf_p_l","_fprintf_s_l","_fscanf_l","_fscanf_s_l","_Locale","_locale_t","_MaxCount","_printf_l","_printf_p","_printf_p_l","_printf_s_l","_scanf_l","_scanf_s_l","_scprintf_l","_scprintf_p","_scprintf_p_l","_SECIMP","_Size","_snprintf_c","_snprintf_c_l","_snprintf_l","_snprintf_s","_snprintf_s_l","_snscanf_l","_snscanf_s","_snscanf_s_l","_sprintf_l","_sprintf_p","_sprintf_p_l","_sprintf_s_l","_Src","_sscanf_l","_sscanf_s_l","_vfprintf_l","_vfprintf_p","_vfprintf_p_l","_vfprintf_s_l","_vprintf_l","_vprintf_p","_vprintf_p_l","_vprintf_s_l","_vscprintf_l","_vscprintf_p","_vscprintf_p_l","_vsnprintf_c","_vsnprintf_c_l","_vsnprintf_l","_vsnprintf_s","_vsnprintf_s_l","_vsprintf_l","_vsprintf_p","_vsprintf_p_l","_vsprintf_s_l","char","const","FILE","fprintf_s","fscanf_s","int","printf_s","scanf_s","size_t","sprintf_s","sscanf_s","va_list","vfprintf_s","vprintf_s","vsnprintf_s","vsprintf_s"]},
{"row":581,"command":"#endif","args":[]},
{"row":583,"command":"","args":["__cdecl","__DEFINE_CPP_OVERLOAD_SECURE_FUNC_0_0","__DEFINE_CPP_OVERLOAD_SECURE_FUNC_0_1_ARGLIST","__DEFINE_CPP_OVERLOAD_SECURE_FUNC_0_2","__DEFINE_CPP_OVERLOAD_SECURE_FUNC_0_2_ARGLIST","__DEFINE_CPP_OVERLOAD_SECURE_FUNC_0_3","_ArgList","_CRTIMP","_DstBuf","_File","_Filename","_Format","_MaxCount","_Mode","_snprintf_s","_Stream","_vsnprintf_s","char","const","errno_t","FILE","fopen_s","freopen_s","get_s","gets_s","int","rsize_t","size_t","sprintf_s","tmpfile_s","tmpnam_s","va_list","vsnprintf_s","vsprintf_s"]},
{"row":601,"command":"#ifndef","args":["_WSTDIO_S_DEFINED"]},
{"row":602,"command":"#define","args":["_WSTDIO_S_DEFINED"," "]},
{"row":603,"command":"","args":["__cdecl","__DEFINE_CPP_OVERLOAD_SECURE_FUNC_0_0","_CRTIMP","_DstBuf","_getws_s","_SizeInWords","_Str","size_t","wchar_t"]},
{"row":606,"command":"#ifdef","args":["_UCRT"]},
{"row":607,"command":"","args":["__builtin_va_end","__builtin_va_list","__builtin_va_start","__cdecl","__int64","__mingw_ovr","__stdio_common_vfwprintf_s","__stdio_common_vfwscanf","__stdio_common_vsnwprintf_s","__stdio_common_vswprintf_s","__stdio_common_vswscanf","_ArgList","_CRT_INTERNAL_LOCAL_PRINTF_OPTIONS","_CRT_INTERNAL_LOCAL_SCANF_OPTIONS","_CRT_INTERNAL_SCANF_SECURECRT","_DstBuf","_DstSize","_File","_Format","_fwprintf_s_l","_fwscanf_s_l","_Len","_Locale","_locale_t","_MaxCount","_Options","_Ret","_snwprintf_s","_snwprintf_s_l","_snwscanf_s","_snwscanf_s_l","_Src","_Str","_swprintf_s_l","_swscanf_s_l","_vfwprintf_s_l","_vfwscanf_s_l","_vsnwprintf_s","_vsnwprintf_s_l","_vsnwscanf_s_l","_vswprintf_s_l","_vswscanf_s_l","_vwprintf_s_l","_vwscanf_s_l","_wprintf_s_l","_wscanf_s_l","const","FILE","fwprintf_s","fwscanf_s","int","NULL","return","size_t","stdin","stdout","swprintf_s","swscanf_s","unsigned","va_list","vfwprintf_s","vfwscanf_s","vswprintf_s","vswscanf_s","vwprintf_s","vwscanf_s","wchar_t","wprintf_s","wscanf_s"]},
{"row":829,"command":"#else","args":[]},
{"row":830,"command":"","args":["__cdecl","_ArgList","_CRTIMP","_Dst","_DstBuf","_DstSize","_DstSizeInWords","_File","_Format","_fwprintf_s_l","_fwscanf_s_l","_Locale","_locale_t","_MaxCount","_SizeInWords","_snwprintf_s","_snwprintf_s_l","_snwscanf_s","_snwscanf_s_l","_Src","_swprintf_s_l","_swscanf_s_l","_vfwprintf_s_l","_vsnwprintf_s","_vsnwprintf_s_l","_vswprintf_s_l","_vwprintf_s_l","_wprintf_s_l","_wscanf_s_l","const","FILE","fwprintf_s","fwscanf_s","int","size_t","swprintf_s","swscanf_s","va_list","vfwprintf_s","vswprintf_s","vwprintf_s","wchar_t","wprintf_s","wscanf_s"]},
{"row":860,"command":"#endif","args":[]},
{"row":862,"command":"","args":["__cdecl","__DEFINE_CPP_OVERLOAD_SECURE_FUNC_0_0","__DEFINE_CPP_OVERLOAD_SECURE_FUNC_0_1_ARGLIST","__DEFINE_CPP_OVERLOAD_SECURE_FUNC_0_2","__DEFINE_CPP_OVERLOAD_SECURE_FUNC_0_2_ARGLIST","__DEFINE_CPP_OVERLOAD_SECURE_FUNC_0_3","_ArgList","_CRTIMP","_Dst","_DstBuf","_File","_Filename","_Format","_MaxCount","_Mode","_OldFile","_SizeInWords","_snwprintf_s","_vsnwprintf_s","_wfopen_s","_wfreopen_s","_wtmpnam_s","const","errno_t","FILE","int","size_t","swprintf_s","va_list","vswprintf_s","wchar_t"]},
{"row":873,"command":"#ifndef","args":["_UCRT"]},
{"row":874,"command":"","args":["__cdecl","__swprintf_l","__vswprintf_l","_ArgList","_Args","_CRTIMP","_Dest","_DstBuf","_File","_Format","_fwprintf_l","_fwprintf_p","_fwprintf_p_l","_fwscanf_l","_Locale","_locale_t","_MaxCount","_Plocinfo","_scwprintf_l","_scwprintf_p","_scwprintf_p_l","_SECIMP","_snwprintf_l","_snwscanf_l","_Src","_swprintf_c_l","_swprintf_p","_swprintf_p_l","_swscanf_l","_vfwprintf_l","_vfwprintf_p","_vfwprintf_p_l","_vscwprintf_l","_vscwprintf_p","_vscwprintf_p_l","_vsnwprintf_l","_vswprintf_c_l","_vswprintf_p","_vswprintf_p_l","_vwprintf_l","_vwprintf_p","_vwprintf_p_l","_wprintf_l","_wprintf_p","_wprintf_p_l","_wscanf_l","const","FILE","int","size_t","va_list","wchar_t"]},
{"row":906,"command":"#endif","args":[]},
{"row":908,"command":"#endif","args":[]},
{"row":909,"command":"#endif","args":[]},
{"row":911,"command":"#if","args":["__MSVCRT_VERSION__","\u003E=","0x800"]},
{"row":912,"command":"","args":["__cdecl","_Count","_CRTIMP","_DstBuf","_DstSize","_ElementSize","_File","_fread_nolock_s","FILE","size_t","void"]},
{"row":913,"command":"#endif","args":[]},
{"row":915,"command":"#ifdef","args":["__cplusplus"]},
{"row":916,"command":"","args":[]},
{"row":917,"command":"#endif","args":[]},
{"row":918,"command":"#endif","args":[]}],
"identifiers":["_INC_STDIO_S","defined","(","__LIBMSVCRT__",")","_SECIMP","__cplusplus","extern","_STDIO_S_DEFINED","_CRTIMP","errno_t","__cdecl","clearerr_s","FILE","_File","size_t","fread_s","void","_DstBuf","_DstSize","_ElementSize","_Count","_UCRT","int","__stdio_common_vsprintf_s","unsigned","__int64","_Options","char","_Str","_Len","const","_Format","_locale_t","_Locale","va_list","_ArgList","__stdio_common_vsprintf_p","__stdio_common_vsnprintf_s","_MaxCount","__stdio_common_vfprintf_s","__stdio_common_vfprintf_p","__mingw_ovr","_vfscanf_s_l","return","__stdio_common_vfscanf","_CRT_INTERNAL_SCANF_SECURECRT","vfscanf_s","NULL","_vscanf_s_l","stdin","vscanf_s","_fscanf_s_l","__builtin_va_list","_Ret","__builtin_va_start","__builtin_va_end","fscanf_s","_scanf_s_l","scanf_s","_vfscanf_l","_vscanf_l","_fscanf_l","_scanf_l","_vsscanf_s_l","_Src","__stdio_common_vsscanf","vsscanf_s","_sscanf_s_l","sscanf_s","_vsscanf_l","_sscanf_l","_snscanf_s_l","_snscanf_s","_snscanf_l","_vfprintf_s_l","vfprintf_s","_vprintf_s_l","stdout","vprintf_s","_fprintf_s_l","_printf_s_l","fprintf_s","printf_s","_vsnprintf_c_l","__stdio_common_vsprintf","_vsnprintf_c","_snprintf_c_l","_snprintf_c","_vsnprintf_s_l","vsnprintf_s","_vsnprintf_s","_snprintf_s_l","_snprintf_s","_vsprintf_s_l","vsprintf_s","_Size","_sprintf_s_l","sprintf_s","_vfprintf_p_l","_vfprintf_p","_vprintf_p_l","_vprintf_p","_fprintf_p_l","_fprintf_p","_printf_p_l","_printf_p","_vsprintf_p_l","_vsprintf_p","_Dst","_sprintf_p_l","_sprintf_p","_vscprintf_p_l","_CRT_INTERNAL_PRINTF_STANDARD_SNPRINTF_BEHAVIOR","_vscprintf_p","_scprintf_p_l","_scprintf_p","_vfprintf_l","__stdio_common_vfprintf","_vprintf_l","_fprintf_l","_printf_l","_vsnprintf_l","_CRT_INTERNAL_PRINTF_LEGACY_VSPRINTF_NULL_TERMINATION","_snprintf_l","_vsprintf_l","_sprintf_l","_vscprintf_l","_scprintf_l","__DEFINE_CPP_OVERLOAD_SECURE_FUNC_0_3","__DEFINE_CPP_OVERLOAD_SECURE_FUNC_0_2","__DEFINE_CPP_OVERLOAD_SECURE_FUNC_0_1_ARGLIST","__DEFINE_CPP_OVERLOAD_SECURE_FUNC_0_2_ARGLIST","fopen_s","_Filename","_Mode","freopen_s","_Stream","gets_s","rsize_t","__DEFINE_CPP_OVERLOAD_SECURE_FUNC_0_0","get_s","tmpfile_s","tmpnam_s","_WSTDIO_S_DEFINED","wchar_t","_getws_s","_SizeInWords","__stdio_common_vswprintf_s","__stdio_common_vsnwprintf_s","__stdio_common_vfwprintf_s","_vfwscanf_s_l","__stdio_common_vfwscanf","_CRT_INTERNAL_LOCAL_SCANF_OPTIONS","vfwscanf_s","_vwscanf_s_l","vwscanf_s","_fwscanf_s_l","fwscanf_s","_wscanf_s_l","wscanf_s","_vswscanf_s_l","__stdio_common_vswscanf","vswscanf_s","_swscanf_s_l","swscanf_s","_vsnwscanf_s_l","_snwscanf_s_l","_snwscanf_s","_vfwprintf_s_l","_CRT_INTERNAL_LOCAL_PRINTF_OPTIONS","_vwprintf_s_l","vfwprintf_s","vwprintf_s","_fwprintf_s_l","_wprintf_s_l","fwprintf_s","wprintf_s","_vswprintf_s_l","vswprintf_s","_swprintf_s_l","swprintf_s","_vsnwprintf_s_l","_vsnwprintf_s","_snwprintf_s_l","_snwprintf_s","_DstSizeInWords","_wfopen_s","_wfreopen_s","_OldFile","_wtmpnam_s","_fwprintf_p","_wprintf_p","_vfwprintf_p","_vwprintf_p","_swprintf_p","_vswprintf_p","_scwprintf_p","_vscwprintf_p","_wprintf_l","_wprintf_p_l","_vwprintf_l","_vwprintf_p_l","_fwprintf_l","_fwprintf_p_l","_vfwprintf_l","_vfwprintf_p_l","_swprintf_c_l","_swprintf_p_l","_vswprintf_c_l","_vswprintf_p_l","_scwprintf_l","_scwprintf_p_l","_vscwprintf_p_l","_snwprintf_l","_vsnwprintf_l","__swprintf_l","_Dest","_Plocinfo","__vswprintf_l","_Args","_vscwprintf_l","_fwscanf_l","_swscanf_l","_snwscanf_l","_wscanf_l","__MSVCRT_VERSION__","\u003E=","0x800","_fread_nolock_s"],
"defines":["_INC_STDIO_S","_SECIMP","_STDIO_S_DEFINED","L_tmpnam_s","TMP_MAX_S","_WSTDIO_S_DEFINED"]}
